{
  "legislative_session": "153",
  "identifier": "SCR 145",
  "title": "DESIGNATING APRIL 11, 2026 AS \u201cNATIONAL PET DAY\u201d IN THE STATE OF DELAWARE.",
  "from_organization": "~{\"classification\": \"upper\"}",
  "classification": [
    "concurrent resolution"
  ],
  "subject": [],
  "abstracts": [
    {
      "note": "synopsis",
      "abstract": "This Senate Concurrent Resolution designates April 11th, 2026, as \u201cNational Pet Day\u201d in the State of Delaware."
    }
  ],
  "other_titles": [],
  "other_identifiers": [
    {
      "identifier": "ocd-bill-de-153-scr145"
    }
  ],
  "actions": [
    {
      "description": "Introduced in Senate",
      "date": "2026-03-12",
      "organization_id": "~{\"classification\": \"upper\"}",
      "classification": [
        "introduction"
      ],
      "related_entities": [],
      "_processing": {
        "log_file_created": "2026-07-13T06:02:25Z"
      }
    },
    {
      "description": "Passed By Senate. Votes: 21 YES",
      "date": "2026-03-12",
      "organization_id": "~{\"classification\": \"upper\"}",
      "classification": [
        "passage"
      ],
      "related_entities": [],
      "_processing": {
        "log_file_created": "2026-07-13T06:02:25Z"
      }
    },
    {
      "description": "Passed In House by Voice Vote",
      "date": "2026-03-12",
      "organization_id": "~{\"classification\": \"lower\"}",
      "classification": [],
      "related_entities": [],
      "_processing": {
        "log_file_created": "2026-07-13T06:02:25Z"
      }
    }
  ],
  "sponsorships": [
    {
      "name": "John \"Jack\" Walsh",
      "classification": "primary",
      "entity_type": "person",
      "primary": true,
      "person_id": "~{\"chamber\": \"upper\", \"name\": \"John \\\"Jack\\\" Walsh\"}",
      "organization_id": null
    },
    {
      "name": "Melanie Ross Levin",
      "classification": "primary",
      "entity_type": "person",
      "primary": true,
      "person_id": "~{\"chamber\": \"lower\", \"name\": \"Melanie Ross Levin\"}",
      "organization_id": null
    },
    {
      "name": "Nicole Poore",
      "classification": "primary",
      "entity_type": "person",
      "primary": true,
      "person_id": "~{\"chamber\": \"upper\", \"name\": \"Nicole Poore\"}",
      "organization_id": null
    },
    {
      "name": "Brian Pettyjohn",
      "classification": "primary",
      "entity_type": "person",
      "primary": true,
      "person_id": "~{\"chamber\": \"upper\", \"name\": \"Brian Pettyjohn\"}",
      "organization_id": null
    }
  ],
  "related_bills": [],
  "versions": [],
  "documents": [],
  "citations": [],
  "sources": [
    {
      "url": "https://legis.delaware.gov/BillDetail?LegislationId=142920",
      "note": "text/html"
    }
  ],
  "extras": {},
  "jurisdiction": {
    "id": "ocd-jurisdiction/country:us/state:de/government",
    "name": "Delaware",
    "classification": "state",
    "division_id": "ocd-division/country:us/state:de"
  },
  "_processing": {
    "logs_latest_update": "2026-07-13T06:02:25Z",
    "text_extraction_latest_update": "2026-07-21T13:41:36.314262Z"
  }
}