{
  "legislative_session": "153",
  "identifier": "HB 257",
  "title": "AN ACT TO AMEND TITLES 11 AND 29 OF THE DELAWARE CODE RELATING TO STATE PENSIONS AND CHILD SEXUAL OFFENSES.",
  "from_organization": "~{\"classification\": \"lower\"}",
  "classification": [
    "bill"
  ],
  "subject": [],
  "abstracts": [
    {
      "note": "synopsis",
      "abstract": "This Act provides for forfeiture of the state\u2019s contribution to a state, judicial, county, or municipal employee\u2019s pension if that employee is convicted of a sexual offense against a child and the offense was in connection with or aided by the employee\u2019s position. It further provides that if a state, judicial, county, or municipal employee is convicted of a sexual offense against a child and the Court finds the offense was committed in connection with or aided by the employee's position, the Court may assign portions of the employee\u2019s pension to the victim of the crime for restitution."
    }
  ],
  "other_titles": [],
  "other_identifiers": [
    {
      "identifier": "ocd-bill-de-153-hb257"
    }
  ],
  "actions": [
    {
      "description": "Introduced and Assigned to Administration Committee in House",
      "date": "2025-12-18",
      "organization_id": "~{\"classification\": \"lower\"}",
      "classification": [
        "introduction",
        "referral-committee"
      ],
      "related_entities": [
        {
          "name": "Administration",
          "entity_type": "organization",
          "organization_id": null
        }
      ],
      "_processing": {
        "log_file_created": "2026-07-13T06:02:26Z"
      }
    }
  ],
  "sponsorships": [
    {
      "name": "Kerri Evelyn Harris",
      "classification": "primary",
      "entity_type": "person",
      "primary": true,
      "person_id": "~{\"chamber\": \"lower\", \"name\": \"Kerri Evelyn Harris\"}",
      "organization_id": null
    },
    {
      "name": "Nicole Poore",
      "classification": "primary",
      "entity_type": "person",
      "primary": true,
      "person_id": "~{\"chamber\": \"upper\", \"name\": \"Nicole Poore\"}",
      "organization_id": null
    },
    {
      "name": "Claire Snyder-Hall",
      "classification": "primary",
      "entity_type": "person",
      "primary": true,
      "person_id": "~{\"chamber\": \"lower\", \"name\": \"Claire Snyder-Hall\"}",
      "organization_id": null
    }
  ],
  "related_bills": [],
  "versions": [
    {
      "note": "Bill Text",
      "links": [
        {
          "url": "https://legis.delaware.gov/json/BillDetail/GenerateHtmlDocument?legislationId=142735&legislationTypeId=1&docTypeId=2&legislationName=HB257",
          "media_type": "text/html"
        },
        {
          "url": "https://legis.delaware.gov/json/BillDetail/GeneratePdfDocument?legislationId=142735&legislationTypeId=1&docTypeId=2&legislationName=HB257",
          "media_type": "application/pdf"
        }
      ],
      "date": "",
      "classification": ""
    }
  ],
  "documents": [],
  "citations": [],
  "sources": [
    {
      "url": "https://legis.delaware.gov/BillDetail?LegislationId=142735",
      "note": "text/html"
    }
  ],
  "extras": {},
  "jurisdiction": {
    "id": "ocd-jurisdiction/country:us/state:de/government",
    "name": "Delaware",
    "classification": "state",
    "division_id": "ocd-division/country:us/state:de"
  },
  "_processing": {
    "logs_latest_update": "2026-07-13T06:02:26Z"
  }
}